{
  "chapters": [
    {
      "id": 1,
      "number": 1,
      "title": "Un genio",
      "pages": 63,
      "volume": 1,
      "coverUrl": "https://static.wikia.nocookie.net/bluelock/images/2/23/Chapter_1_%28Episode_Nagi%29_Colored_Page.png"
    },
    {
      "id": 2,
      "number": 2,
      "title": "Promesa",
      "pages": 58,
      "volume": 1,
      "coverUrl": "https://static.wikia.nocookie.net/bluelock/images/6/64/Chapter_2_%28Episode_Nagi%29.png/revision/latest?cb=20221129160632"
    },
        {
      "id": 3,
      "number": 3,
      "title": "Idiota",
      "pages": 39,
      "volume": 1,
      "coverUrl": "https://static.wikia.nocookie.net/bluelock/images/c/c4/Chapter_3_%28Episode_Nagi%29.png/revision/latest?cb=20221129160636"
    },
        {
      "id": 4,
      "number": 4,
      "title": "El juego",
      "pages": 36,
      "volume": 1,
      "coverUrl": "https://static.wikia.nocookie.net/bluelock/images/1/1b/Chapter_4_%28Episode_Nagi%29.png/revision/latest?cb=20221129160640"
    },
        {
      "id": 5,
      "number": 5,
      "title": "Vs. Equipo Y",
      "pages": 49,
      "volume": 1,
      "coverUrl": "https://static.wikia.nocookie.net/bluelock/images/d/d3/Chapter_5_%28Episode_Nagi%29.png/revision/latest?cb=20221130054643"
    }
    
  ]
}
